annalist_root/__init__.py
annalist_root/bashtest.sh
annalist_root/devel_site_init.sh
annalist_root/devel_sitedata_update.sh
annalist_root/gunicorn_server.sh
annalist_root/makeemptysitedata.sh
annalist_root/maketestsitedata.sh
annalist_root/manage.py
annalist_root/old_makedevelsitedata.sh
annalist_root/old_makepersonalsitedata.sh
annalist_root/requirements.txt
annalist_root/rundevserver.sh
annalist_root/rundevserver_fast.sh
annalist_root/rundoctests.py
annalist_root/runserver.sh
annalist_root/runtest.sh
annalist_root/runtests.sh
annalist_root/settings.sh
annalist_root/test-coverage.sh
annalist_root/annalist/__init__.py
annalist_root/annalist/admin.py
annalist_root/annalist/apps.py
annalist_root/annalist/collections_data.py
annalist_root/annalist/exceptions.py
annalist_root/annalist/identifiers.py
annalist_root/annalist/layout.py
annalist_root/annalist/message.py
annalist_root/annalist/resourcetypes.py
annalist_root/annalist/urls.py
annalist_root/annalist/util.py
annalist_root/annalist/data/Annalist_schema/entitydata/Class/type_data_meta.jsonld
annalist_root/annalist/data/Annalist_schema/entitydata/Class/Audio/entity_data.jsonld
annalist_root/annalist/data/Annalist_schema/entitydata/Class/Collection/entity_data.jsonld
annalist_root/annalist/data/Annalist_schema/entitydata/Class/Default_type/entity_data.jsonld
annalist_root/annalist/data/Annalist_schema/entitydata/Class/Entity/entity_data.jsonld
annalist_root/annalist/data/Annalist_schema/entitydata/Class/EntityData/entity_data.jsonld
annalist_root/annalist/data/Annalist_schema/entitydata/Class/EntityRoot/entity_data.jsonld
annalist_root/annalist/data/Annalist_schema/entitydata/Class/Enum/entity_data.jsonld
annalist_root/annalist/data/Annalist_schema/entitydata/Class/Enum_field_placement/entity_data.jsonld
annalist_root/annalist/data/Annalist_schema/entitydata/Class/Enum_list_type/entity_data.jsonld
annalist_root/annalist/data/Annalist_schema/entitydata/Class/Enum_render_type/entity_data.jsonld
Annalist-0.5.18.dist-info/LICENCE.txt
Annalist-0.5.18.dist-info/METADATA
Annalist-0.5.18.dist-info/WHEEL
Annalist-0.5.18.dist-info/entry_points.txt
Annalist-0.5.18.dist-info/top_level.txt
Annalist-0.5.18.dist-info/RECORD
