Metadata-Version: 2.1
Name: Annalist
Version: 0.5.18
Summary: Annalist linked data notebook
Home-page: https://github.com/gklyne/annalist
Author: Graham Klyne
Author-email: gk-pypi@ninebynine.org
License: MIT
Platform: UNKNOWN
Classifier: Development Status :: 3 - Alpha
Classifier: Environment :: Web Environment
Classifier: Intended Audience :: Developers
Classifier: Intended Audience :: Science/Research
Classifier: Intended Audience :: End Users/Desktop
Classifier: License :: OSI Approved :: MIT License
Classifier: Operating System :: OS Independent
Classifier: Programming Language :: Python :: 3.9
License-File: LICENCE.txt
Requires-Dist: Django (==4.0.3)
Requires-Dist: packaging (==21.3)
Requires-Dist: six (==1.16.0)
Requires-Dist: requests (==2.26.0)
Requires-Dist: urllib3 (==1.26.7)
Requires-Dist: idna (==3.3)
Requires-Dist: requests-oauthlib (==1.3.0)
Requires-Dist: oauthlib (==3.1.1)
Requires-Dist: certifi (==2021.10.8)
Requires-Dist: httplib2 (==0.20.2)
Requires-Dist: rdflib (==6.1.1)
Requires-Dist: isodate (==0.6.0)
Requires-Dist: pyparsing (==3.0.6)
Requires-Dist: Markdown (==3.3.6)
Requires-Dist: gunicorn (==20.1.0)
Requires-Dist: httpretty (==1.1.4)
Requires-Dist: beautifulsoup4 (==4.10.0)
